aws_utils_app/__init__.py
aws_utils_app/core.py
aws_utils_app-0.5.3.dist-info/METADATA
aws_utils_app-0.5.3.dist-info/WHEEL
aws_utils_app-0.5.3.dist-info/top_level.txt
aws_utils_app-0.5.3.dist-info/RECORD
