Metadata-Version: 2.4
Name: aws_utils_app
Version: 0.5.3
Summary: Facilitador de integração com serviços AWS como SNS, SQS, Lambda, DynamoDB, RDS e S3
Home-page: https://github.com/matheuszcabral/aws_easy_tools
Author: Matheus Cabral
Author-email: Matheus Cabral <matheuszcabral@gmail.com>
License: MIT
Requires-Python: >=3.7
Requires-Dist: boto3
Requires-Dist: sqlalchemy
